README.txt
bootstrap.py
buildout.cfg
setup.py
docs/HISTORY.txt
src/megrok/__init__.py
src/megrok.z3cform.ui.egg-info/PKG-INFO
src/megrok.z3cform.ui.egg-info/SOURCES.txt
src/megrok.z3cform.ui.egg-info/dependency_links.txt
src/megrok.z3cform.ui.egg-info/entry_points.txt
src/megrok.z3cform.ui.egg-info/namespace_packages.txt
src/megrok.z3cform.ui.egg-info/not-zip-safe
src/megrok.z3cform.ui.egg-info/requires.txt
src/megrok.z3cform.ui.egg-info/top_level.txt
src/megrok/z3cform/__init__.py
src/megrok/z3cform/ui/README.txt
src/megrok/z3cform/ui/__init__.py
src/megrok/z3cform/ui/configure.zcml
src/megrok/z3cform/ui/ftesting.zcml
src/megrok/z3cform/ui/tests/__init__.py
src/megrok/z3cform/ui/tests/test_defaultRequest.py