Metadata-Version: 1.0
Name: megrok.z3cform.ui
Version: 0.5
Summary: Installation Helper for z3c.formui
Home-page: UNKNOWN
Author: Christian Klinger
Author-email: cklinger@novareto.de
License: GPL
Keywords: grok z3c.form megrok.z3cform.ui
Platform: UNKNOWN
Classifier: Programming Language :: Python
Classifier: Topic :: Software Development :: Libraries :: Python Modules
